gliner_finetune/__init__.py
gliner_finetune/convert.py
gliner_finetune/synthetic.py
gliner_finetune/train.py
gliner_finetune-0.0.4.dist-info/METADATA
gliner_finetune-0.0.4.dist-info/WHEEL
gliner_finetune-0.0.4.dist-info/top_level.txt
gliner_finetune-0.0.4.dist-info/RECORD
