Metadata-Version: 2.1
Name: gliner-finetune
Version: 0.0.4
Summary: A library to create synthetic data with OpenAI and train a GLiNER model on that data.
Home-page: https://github.com/wjbmattingly/gliner-finetune
Author: William J.B. Mattingly
Classifier: Development Status :: 3 - Alpha
Classifier: Intended Audience :: Developers
Classifier: Intended Audience :: Science/Research
Classifier: License :: OSI Approved :: MIT License
Classifier: Natural Language :: English
Classifier: Operating System :: OS Independent
Classifier: Programming Language :: Python :: 3
Classifier: Programming Language :: Python :: 3.7
Classifier: Programming Language :: Python :: 3.8
Classifier: Programming Language :: Python :: 3.9
Classifier: Programming Language :: Python :: 3.10
Classifier: Topic :: Software Development :: Libraries :: Python Modules
Classifier: Topic :: Scientific/Engineering :: Artificial Intelligence
Requires-Python: >=3.7, <=3.11
Requires-Dist: gliner
Requires-Dist: openai
Requires-Dist: spacy
Requires-Dist: scipy (==1.12)
Requires-Dist: torch
Requires-Dist: transformers
Requires-Dist: tqdm
Requires-Dist: python-dotenv
